domain_analysis_reporter/__init__.py
domain_analysis_reporter/domain_analysis_reporter.py
domain_analysis_reporter/script.py
domain_analysis_reporter/website_analysis.py
domain_analysis_reporter-0.3.0.dist-info/LICENSE
domain_analysis_reporter-0.3.0.dist-info/METADATA
domain_analysis_reporter-0.3.0.dist-info/WHEEL
domain_analysis_reporter-0.3.0.dist-info/entry_points.txt
domain_analysis_reporter-0.3.0.dist-info/top_level.txt
domain_analysis_reporter-0.3.0.dist-info/RECORD
