Metadata-Version: 2.2
Name: domain_analysis_reporter
Version: 0.3.0
Summary: Command line utility for analysis domain names and reporting useful information
Home-page: https://github.com/benmathat/domain_analysis_reporter
Author: Ben Thomas
Author-email: ben@smallercircle.com
Classifier: Programming Language :: Python :: 3
Classifier: License :: OSI Approved :: MIT License
Classifier: Operating System :: OS Independent
Requires-Python: >=3.10
License-File: LICENSE
Requires-Dist: requests
Requires-Dist: tldextract
Requires-Dist: python-whois
Requires-Dist: boilerpy3
